envlogger/__init__.py
envlogger/environment_logger.py
envlogger/environment_logger_test.py
envlogger/environment_wrapper.py
envlogger/reader.py
envlogger/setup.py
envlogger/step_data.py
envlogger/backends/__init__.py
envlogger/backends/backend_reader.py
envlogger/backends/backend_type.py
envlogger/backends/backend_writer.py
envlogger/backends/in_memory_backend.py
envlogger/backends/in_memory_backend_test.py
envlogger/backends/riegeli_backend_reader.py
envlogger/backends/riegeli_backend_writer.py
envlogger/backends/riegeli_backend_writer_test.py
envlogger/backends/rlds_utils.py
envlogger/backends/rlds_utils_test.py
envlogger/backends/schedulers.py
envlogger/backends/schedulers_test.py
envlogger/backends/tfds_backend_testlib.py
envlogger/backends/tfds_backend_writer.py
envlogger/backends/tfds_backend_writer_test.py
envlogger/backends/cc/__init__.py
envlogger/backends/python/__init__.py
envlogger/backends/python/episode_info.cpython-311-x86_64-linux-gnu.so
envlogger/backends/python/episode_info_test.py
envlogger/backends/python/riegeli_dataset_reader.cpython-311-x86_64-linux-gnu.so
envlogger/backends/python/riegeli_dataset_test.py
envlogger/backends/python/riegeli_dataset_writer.cpython-311-x86_64-linux-gnu.so
envlogger/converters/__init__.py
envlogger/converters/codec.py
envlogger/converters/codec_test.py
envlogger/converters/spec_codec.py
envlogger/converters/spec_codec_test.py
envlogger/examples/__init__.py
envlogger/examples/random_agent_catch.py
envlogger/examples/tfds_random_agent_catch.py
envlogger/proto/__init__.py
envlogger/proto/storage_pb2.py
envlogger/proto/storage_pb2_grpc.py
envlogger/testing/__init__.py
envlogger/testing/catch_env.py
envlogger-1.2.dist-info/LICENSE
envlogger-1.2.dist-info/METADATA
envlogger-1.2.dist-info/WHEEL
envlogger-1.2.dist-info/top_level.txt
envlogger-1.2.dist-info/RECORD
